Metadata-Version: 1.1
Name: itunesxmlgenerator
Version: 0.1
Summary: iTunes xml generator
Home-page: https://github.com/perminovs/iTunesXmlGen
Author: Perminov Sergey
Author-email: UNKNOWN
License: UNKNOWN
Platform: UNKNOWN
Classifier: Programming Language :: Python :: 3
Classifier: License :: OSI Approved :: MIT License
Classifier: Operating System :: OS Independent
